README.md
setup.py
gw2/__init__.py
gw2.egg-info/PKG-INFO
gw2.egg-info/SOURCES.txt
gw2.egg-info/dependency_links.txt
gw2.egg-info/not-zip-safe
gw2.egg-info/requires.txt
gw2.egg-info/top_level.txt