Metadata-Version: 2.1
Name: gw2
Version: 0.0.1
Summary: Guild Wars 2 API client for Python.
Home-page: https://github.com/marella/python-gw2
Author: Ravindra Marella
Author-email: mv.ravindra007@gmail.com
License: MIT
Project-URL: Documentation, https://marella.github.io/python-gw2/
Project-URL: Source Code, https://github.com/marella/python-gw2
Project-URL: Bug Tracker, https://github.com/marella/python-gw2/issues
Keywords: gw2 guild-wars-2 api client
Platform: UNKNOWN
Classifier: Development Status :: 1 - Planning
Classifier: Intended Audience :: Developers
Classifier: License :: OSI Approved :: MIT License
Classifier: Programming Language :: Python :: 2
Classifier: Programming Language :: Python :: 2.7
Classifier: Programming Language :: Python :: 3
Classifier: Programming Language :: Python :: 3.4
Classifier: Programming Language :: Python :: 3.5
Classifier: Programming Language :: Python :: 3.6
Classifier: Topic :: Software Development
Classifier: Topic :: Software Development :: Libraries
Classifier: Topic :: Software Development :: Libraries :: Python Modules
